Metadata-Version: 2.1
Name: LammpsFileManipulation
Version: 0.17
Summary: This is a package designed to help streamline the process of preprocessing LAMMPS output files for scientific calculations/manipulations in Python. The class structures are built using pandas DataFrames making it easy to manipulate.
Home-page: https://github.com/AaronSchwan/LammpsFileManipulation
Author: Aaron Schwan
Author-email: schwanaaron@gmail.com
License: MIT
Download-URL: https://github.com/AaronSchwan/LammpsFileManipulation/releases/tag/v_0.17-alpha
Keywords: LAMMPS,atomistic,dump file
Platform: UNKNOWN
Classifier: Development Status :: 3 - Alpha
Classifier: Intended Audience :: Developers
Classifier: Topic :: Software Development :: Build Tools
Classifier: License :: OSI Approved :: MIT License
Classifier: Programming Language :: Python :: 3
Classifier: Programming Language :: Python :: 3.6
Classifier: Programming Language :: Python :: 3.7
Classifier: Programming Language :: Python :: 3.8
